kdmt/__init__.py
kdmt/__sentence_splitter.py
kdmt/bools.py
kdmt/cache.py
kdmt/checksum.py
kdmt/color.py
kdmt/convert.py
kdmt/csv.py
kdmt/custom_types.py
kdmt/data_structures.py
kdmt/dates.py
kdmt/debug.py
kdmt/df.py
kdmt/dict.py
kdmt/disk.py
kdmt/download.py
kdmt/errors.py
kdmt/file.py
kdmt/functions.py
kdmt/geometry.py
kdmt/html.py
kdmt/infer.py
kdmt/jupyter.py
kdmt/lazy_collections.py
kdmt/lib.py
kdmt/lists.py
kdmt/localized_dateutil.py
kdmt/lock.py
kdmt/main.py
kdmt/matrix.py
kdmt/misc.py
kdmt/ngrams.py
kdmt/numerical.py
kdmt/objects.py
kdmt/outliers.py
kdmt/parallel.py
kdmt/path.py
kdmt/probability.py
kdmt/progress.py
kdmt/progress_bar.py
kdmt/properties.py
kdmt/sequences.py
kdmt/similarity.py
kdmt/statistics.py
kdmt/strings.py
kdmt/text.py
kdmt/tqdm_lib.py
kdmt/version.py
kdmt/wget.py
kdmt/zip.py
kdmt/cloud/__init__.py
kdmt/cloud/azure.py
kdmt/cloud/google.py
kdmt/cloud/s3.py
kdmt/dateinfer/__init__.py
kdmt/dateinfer/constants.py
kdmt/dateinfer/date_elements.py
kdmt/dateinfer/date_fragment.py
kdmt/dateinfer/infer.py
kdmt/dateinfer/ruleproc.py
kdmt/dateinfer/tests.py
kdmt/dateparser/__init__.py
kdmt/dateparser/conf.py
kdmt/dateparser/date.py
kdmt/dateparser/date_parser.py
kdmt/dateparser/freshness_date_parser.py
kdmt/dateparser/parser.py
kdmt/dateparser/settings.py
kdmt/dateparser/timezone_parser.py
kdmt/dateparser/timezones.py
kdmt/dateparser/data/__init__.py
kdmt/dateparser/data/languages_info.py
kdmt/dateparser/data/date_translation_data/__init__.py
kdmt/dateparser/data/date_translation_data/af.py
kdmt/dateparser/data/date_translation_data/agq.py
kdmt/dateparser/data/date_translation_data/ak.py
kdmt/dateparser/data/date_translation_data/am.py
kdmt/dateparser/data/date_translation_data/ar.py
kdmt/dateparser/data/date_translation_data/as.py
kdmt/dateparser/data/date_translation_data/asa.py
kdmt/dateparser/data/date_translation_data/ast.py
kdmt/dateparser/data/date_translation_data/az-Cyrl.py
kdmt/dateparser/data/date_translation_data/az-Latn.py
kdmt-1.0.73.dist-info/LICENSE
kdmt-1.0.73.dist-info/METADATA
kdmt-1.0.73.dist-info/WHEEL
kdmt-1.0.73.dist-info/top_level.txt
kdmt-1.0.73.dist-info/RECORD
