Metadata-Version: 2.1
Name: kdmt
Version: 1.0.73
Summary: Various handy functions and objects
Home-page: https://github.com/mbenhaddou/pyutilities
Author: Mohamed Ben Haddou
Author-email: haddomoh@gmail.com
Classifier: Programming Language :: Python :: 3
Classifier: Operating System :: OS Independent
Classifier: License :: OSI Approved :: GNU Lesser General Public License v3 or later (LGPLv3+)
Classifier: Topic :: Software Development :: Libraries
Requires-Python: >=3.6
License-File: LICENSE
Requires-Dist: pandas
Requires-Dist: scikit-learn
Requires-Dist: simplejson
Requires-Dist: numpy
Requires-Dist: requests
Requires-Dist: decorator
Requires-Dist: urlparser
Requires-Dist: tqdm
Requires-Dist: progressbar
Requires-Dist: regex
Requires-Dist: matplotlib
Requires-Dist: importlib-resources
Requires-Dist: importlib-metadata
Requires-Dist: azure-storage-blob
